ionic_langchain/__init__.py
ionic_langchain/prompt.py
ionic_langchain/tool.py
ionic_langchain-0.2.3.dist-info/METADATA
ionic_langchain-0.2.3.dist-info/WHEEL
ionic_langchain-0.2.3.dist-info/RECORD
