Metadata-Version: 2.1
Name: ionic-langchain
Version: 0.2.3
Summary: 
Author: Owen Sims
Author-email: owen@ionicapi.com
Requires-Python: >=3.8.12,<4.0.0
Classifier: Programming Language :: Python :: 3
Classifier: Programming Language :: Python :: 3.9
Classifier: Programming Language :: Python :: 3.10
Classifier: Programming Language :: Python :: 3.11
Requires-Dist: ionic-api-sdk (>=0.7.0,<0.8.0)
Requires-Dist: langchain (>=0.1.0,<0.2.0)
Requires-Dist: pytest (>=7.4.4,<8.0.0)
